[
  {
    "title": "TIGSource Update #1",
    "author": "Drëw",
    "date": 1477829171,
    "image": "http://i.imgur.com/zc4tcve.gif",
    "filepath": "archive/0.md",
    "tags": ["TIG"]
  },
  {
    "title": "TIGSource Update #2",
    "author": "Drëw",
    "date": 1477920258,
    "image": "http://i.imgur.com/Z04VVhL.png",
    "filepath": "archive/1.md",
    "tags": ["TIG"]
  },
  {
    "title": "TIGSource Update #3",
    "author": "Drëw",
    "date": 1478016782,
    "image": "http://i.imgur.com/3GQUGrw.gif",
    "filepath": "archive/2.md",
    "tags": ["TIG"]
  },
  {
    "title": "TIGSource Update #4",
    "author": "Drëw",
    "date": 1478125280,
    "image": "https://i.ytimg.com/vi/PAiyiR0E_MU/hqdefault.jpg",
    "filepath": "archive/3.md",
    "tags": ["TIG"]
  },
  {
    "title": "TIGSource Update #5",
    "author": "Drëw",
    "date": 1478759129,
    "image": "https://i.ytimg.com/vi/clEoU64XWGI/hqdefault.jpg",
    "filepath": "archive/4.md",
    "tags": ["TIG"]
  },
  {
    "title": "TIGSource Update #6",
    "author": "Drëw",
    "date": 1479075320,
    "image": "http://i.imgur.com/pBLQGSe.png",
    "filepath": "archive/5.md",
    "tags": ["TIG"]
  },
  {
    "title": "TIGSource Update #7",
    "author": "Drëw",
    "date": 1479700677,
    "image": "http://i.imgur.com/DTck1my.png",
    "filepath": "archive/6.md",
    "tags": ["TIG"]
  },
  {
    "title": "TIGSource Update #8",
    "author": "Drëw",
    "date": 1480046136,
    "image": "https://i.ytimg.com/vi/817AsuNWJZE/hqdefault.jpg",
    "filepath": "archive/7.md",
    "tags": ["TIG"]
  },
  {
    "title": "TIGSource Update #9",
    "author": "Drëw",
    "date": 1480908755,
    "image": "http://i.imgur.com/FIa6ZQ8.png",
    "filepath": "archive/8.md",
    "tags": ["TIG"]
  },
  {
    "title": "TIGSource Update #10",
    "author": "Drëw",
    "date": 1481048428,
    "image": "http://i.imgur.com/Cr9q5VV.png",
    "filepath": "archive/9.md",
    "tags": ["TIG"]
  },
  {
    "title": "TIGSource Update #11",
    "author": "Drëw",
    "date": 1481353001,
    "image": "https://i.ytimg.com/vi/0O9E7NC1Xd8/hqdefault.jpg",
    "filepath": "archive/10.md",
    "tags": ["TIG"]
  },
  {
    "title": "TIGSource Update #12",
    "author": "Drëw",
    "date": 1482795145,
    "image": "https://media.giphy.com/media/26ybuMkqFgnMjjv0I/source.gif",
    "filepath": "archive/11.md",
    "tags": ["TIG"]
  },
  {
    "title": "TIGSource Update #13",
    "author": "Drëw",
    "date": 1485013238,
    "image": "http://i.imgur.com/1lYGJD7.png",
    "filepath": "archive/12.md",
    "tags": ["TIG"]
  },
  {
    "title": "TIGSource Update #14",
    "author": "Drëw",
    "date": 1485624898,
    "image": "http://i.imgur.com/cdzd7f7.png",
    "filepath": "archive/13.md",
    "tags": ["TIG"]
  },
  {
    "title": "TIGSource Update #15",
    "author": "Drëw",
    "date": 1486195984,
    "image": "http://i.imgur.com/8lcDndu.png",
    "filepath": "archive/14.md",
    "tags": ["TIG"]
  },
  {
    "title": "TIGSource Update #16",
    "author": "Drëw",
    "date": 1486966550,
    "image": "http://i.imgur.com/30CcBNy.png",
    "filepath": "archive/15.md",
    "tags": ["TIG"]
  },
  {
    "title": "TIGSource Update #17",
    "author": "Drëw",
    "date": 1487448557,
    "image": "http://i.imgur.com/Vd5n6dT.png",
    "filepath": "archive/16.md",
    "tags": ["TIG"]
  },
  {
    "title": "TIGSource Update #18 - Tech Demo Release!",
    "author": "Drëw",
    "date": 1488044433,
    "image": "https://pbs.twimg.com/media/Ci4dT0bU4AAkM1_.jpg:large",
    "filepath": "archive/17.md",
    "tags": ["TIG", "RELEASE"]
  },
  {
    "title": "TIGSource Update #19",
    "author": "Drëw",
    "date": 1492282247,
    "image": "http://i.imgur.com/yA1l3C0.jpg",
    "filepath": "archive/18.md",
    "tags": ["TIG"]
  },
  {
    "title": "TIGSource Update #20",
    "author": "Drëw",
    "date": 1492631294,
    "image": "https://i.ytimg.com/vi/Y7y884s38b4/sddefault.jpg",
    "filepath": "archive/19.md",
    "tags": ["TIG"]
  },
  {
    "title": "TIGSource Update #21",
    "author": "Drëw",
    "date": 1493461102,
    "image": "http://i.imgur.com/4s33kNR.png",
    "filepath": "archive/20.md",
    "tags": ["TIG"]
  },
  {
    "title": "TIGSource Update #22",
    "author": "Drëw",
    "date": 1494663796,
    "image": "http://i.imgur.com/JiAchDo.png",
    "filepath": "archive/21.md",
    "tags": ["TIG"]
  },
  {
    "title": "TIGSource Update #23",
    "author": "Drëw",
    "date": 1496063718,
    "image": "https://i.ytimg.com/vi/FfQ1rG6I2Cs/sddefault.jpg",
    "filepath": "archive/22.md",
    "tags": ["TIG"]
  },
  {
    "title": "TIGSource Update #24",
    "author": "Drëw",
    "date": 1498390724,
    "image": "http://i.imgur.com/IhaN4SF.png",
    "filepath": "archive/23.md",
    "tags": ["TIG"]
  },
  {
    "title": "TIGSource Update #25",
    "author": "Drëw",
    "date": 1502054495,
    "image": "http://i.imgur.com/ujN81Y3.png",
    "filepath": "archive/24.md",
    "tags": ["TIG"]
  },
  {
    "title": "TIGSource Update #26",
    "author": "Drëw",
    "date": 1502297234,
    "image": "http://i.imgur.com/OPoZVsJ.png",
    "filepath": "archive/25.md",
    "tags": ["TIG"]
  },
  {
    "title": "TIGSource Lost Updates",
    "author": "Drëw",
    "date": 1502637646,
    "image": "https://gifyu.com/images/test37add.gif",
    "filepath": "archive/26.md",
    "tags": ["TIG", "ANNOUNCEMENT"]
  },
  {
    "title": "TIGSource Update #27",
    "author": "Drëw",
    "date": 1505579613,
    "image": "https://i.ytimg.com/vi/CNk3nedo-gE/sddefault.jpg",
    "filepath": "archive/27.md",
    "tags": ["TIG"]
  },
  {
    "title": "TIGSource Update #28",
    "author": "Drëw",
    "date": 1511563693,
    "image": "https://i.imgur.com/JfB1FHz.png",
    "filepath": "archive/28.md",
    "tags": ["TIG"]
  },
  {
    "title": "TIGSource Update #29",
    "author": "Drëw",
    "date": 1519578810,
    "image": "https://i.ytimg.com/vi/RjeVKaQ2kLk/sddefault.jpg",
    "filepath": "archive/29.md",
    "tags": ["TIG"]
  },
  {
    "title": "TIGSource Update #30",
    "author": "Drëw",
    "date": 1519659900,
    "image": "https://i.imgur.com/Ylo7pSD.png",
    "filepath": "archive/30.md",
    "tags": ["TIG"]
  },
  {
    "title": "TIGSource Update #31",
    "author": "Drëw",
    "date": 1520169499,
    "image": "https://i.ytimg.com/vi/jgNDcnPjhFY/sddefault.jpg",
    "filepath": "archive/31.md",
    "tags": ["TIG"]
  },
  {
    "title": "TIGSource Update #32",
    "author": "Drëw",
    "date": 1528676281,
    "image": "https://i.imgur.com/pvB6L50.png",
    "filepath": "archive/32.md",
    "tags": ["TIG"]
  },
  {
    "title": "TIGSource Update #33",
    "author": "Drëw",
    "date": 1528814720,
    "image": "http://via.placeholder.com/300x300?text=No+Image+Available",
    "filepath": "archive/33.md",
    "tags": ["TIG"]
  },
  {
    "title": "TIGSource Update #34",
    "author": "Drëw",
    "date": 1529270834,
    "image": "http://via.placeholder.com/300x300?text=No+Image+Available",
    "filepath": "archive/34.md",
    "tags": ["TIG"]
  },
  {
    "title": "TIGSource Update #35",
    "author": "Drëw",
    "date": 1530166256,
    "image": "http://via.placeholder.com/300x300?text=No+Image+Available",
    "filepath": "archive/35.md",
    "tags": ["TIG"]
  },
  {
    "title": "TIGSource Update #36",
    "author": "Drëw",
    "date": 1533466880,
    "image": "https://i.imgur.com/6ZMlM3A.png",
    "filepath": "archive/36.md",
    "tags": ["TIG"]
  },
  {
    "title": "TIGSource Update #37",
    "author": "Drëw",
    "date": 1533896223,
    "image": "https://i.ytimg.com/vi/TbXeLSx6TjI/sddefault.jpg",
    "filepath": "archive/37.md",
    "tags": ["TIG"]
  },
  {
    "title": "What Happened With Mainasutto?",
    "author": "Drëw",
    "date": 1570575120,
    "image": "https://i.ytimg.com/vi/PZA4SVkwc2U/hqdefault.jpg",
    "filepath": "announcement/0.md",
    "tags": ["ANNOUNCEMENT", "VIDEO"]
  },
  {
    "title": "TIGSource Update #38",
    "author": "Drëw",
    "date": 1576950723,
    "image": "https://i.imgur.com/O9riYMg.png",
    "filepath": "archive/38.md",
    "tags": ["TIG"]
  },
  {
    "title": "TIGSource Update #39",
    "author": "Drëw",
    "date": 1577348098,
    "image": "https://i.imgur.com/X8iHQn3.png",
    "filepath": "archive/39.md",
    "tags": ["TIG"]
  },
  {
    "title": "TIGSource Update #40",
    "author": "Drëw",
    "date": 1577551953,
    "image": "https://i.imgur.com/LpTAEv5.png",
    "filepath": "archive/40.md",
    "tags": ["TIG"]
  },
  {
    "title": "Devlog - Cameras & Backgrounds",
    "author": "Drëw",
    "date": 1588010280,
    "image": "https://i.ytimg.com/vi/DpOLguv-cz4/hqdefault.jpg",
    "filepath": "video/0.md",
    "tags": ["VIDEO"]
  },
  {
    "title": "Devlog - Enemies & Hitboxes",
    "author": "Drëw",
    "date": 1589652840,
    "image": "https://i.ytimg.com/vi/e7hdXCT7SpY/hqdefault.jpg",
    "filepath": "video/1.md",
    "tags": ["VIDEO"]
  },
  {
    "title": "Devlog - Cutscenes, New Player and more!",
    "author": "Drëw",
    "date": 1591462620,
    "image": "https://i.ytimg.com/vi/7QZoZVSz35Y/hqdefault.jpg",
    "filepath": "video/2.md",
    "tags": ["VIDEO"]
  },
  {
    "title": "Itch.io Page + Demo Release Date!",
    "author": "Drëw",
    "date": 1655398320,
    "image": "https://i.imgur.com/UeVzV82.png",
    "filepath": "announcement/1.md",
    "tags": ["ANNOUNCEMENT"]
  },
  {
    "title": "Linked Mask - Steam Release!",
    "author": "Drëw",
    "date": 1676501940,
    "image": "https://cdn.cloudflare.steamstatic.com/steam/apps/1111590/capsule_616x353.jpg",
    "filepath": "announcement/3.md",
    "tags": ["ANNOUNCEMENT"]
  },
  {
    "title": "Almost 8 years now...",
    "author": "Drëw",
    "date": 1685724720,
    "image": "https://i.imgur.com/1m4bYiW.png",
    "filepath": "announcement/2.md",
    "tags": ["ANNOUNCEMENT"]
  },
  {
    "title": "New Gamejolt Page!",
    "author": "Drëw",
    "date": 1692312060,
    "image": "https://m.gjcdn.net/game-thumbnail/500/160593-crop392_45_1543_692-ttbh6t8n-v4.jpg",
    "filepath": "announcement/4.md",
    "tags": ["ANNOUNCEMENT"]
  },
  {
    "title": "Mainasutto is finally on IndieDB",
    "author": "Drëw",
    "date": 1685724300,
    "image": "https://i.imgur.com/LXr8HTV.png",
    "filepath": "announcement/5.md",
    "tags": ["ANNOUNCEMENT"]
  },
  {
    "title": "Devbuild 23w10",
    "author": "Drëw",
    "date": 1682126940,
    "image": "https://i.imgur.com/lZWgm3m.png",
    "filepath": "release/0.md",
    "tags": ["RELEASE"]
  },
  {
    "title": "Devbuild 23w24",
    "author": "Drëw",
    "date": 1687361400,
    "image": "https://i.imgur.com/zbV5MWf.png",
    "filepath": "release/1.md",
    "tags": ["RELEASE"]
  },
  {
    "title": "Finally working on a Steam Page",
    "author": "Drëw",
    "date": 1693343400,
    "image": "https://i.imgur.com/lV0PZXE.png",
    "filepath": "announcement/6.md",
    "tags": ["ANNOUNCEMENT"]
  },
  {
    "title": "Devbuild 23w36",
    "author": "Drëw",
    "date": 1694553420,
    "image": "https://i.imgur.com/5HVx1N7.png",
    "filepath": "release/2.md",
    "tags": ["RELEASE"]
  },
  {
    "title": "Wishlist Mainasutto on Steam!",
    "author": "Drëw",
    "date": 1695692820,
    "image": "https://i.imgur.com/qzu5XLo.png",
    "filepath": "announcement/7.md",
    "tags": ["ANNOUNCEMENT"]
  },
  {
    "title": "New Mainasutto Trailer for Steam Page",
    "author": "Drëw",
    "date": 1697427180,
    "image": "https://i.ytimg.com/vi/dJ1ga67zW-0/hqdefault.jpg",
    "filepath": "announcement/8.md",
    "tags": ["VIDEO"]
  },
  {
    "title": "Moving to Canada",
    "author": "Drëw",
    "date": 1711002300,
    "image": "https://pbs.twimg.com/media/GJ1aWRXXoAAEwdc?format=jpg",
    "filepath": "life/0.md",
    "tags": ["LIFE"]
  },
  {
    "title": "I'm still alive!",
    "author": "Drëw",
    "date": 1715921700,
    "image": "https://i.imgur.com/q2Klc5W.png",
    "filepath": "life/1.md",
    "tags": ["ANNOUNCEMENT", "LIFE"]
  },
  {
    "title": "New Page, New Blog & More!",
    "author": "Drëw",
    "date": 1716911458,
    "image": "https://i.imgur.com/SLOAaIV.png",
    "filepath": "newsletter/0.md",
    "tags": ["ANNOUNCEMENT", "NEWSLETTER"]
  }
]
